<maps>
<map i="1"><f i="1" d="57,58,59,60"/><f i="2" d="61,62,63,64"/><f i="3" d="123,124,125"/><f i="4" d="17,18,19,20"/><f i="5" d="93,94,95,96"/><f i="6" d="85,86,87,88"/><f i="7" d="105,106,107"/><f i="8" d="29,30,31,32"/><f i="9" d="73,74,75,76"/><f i="10" d="77,78,79,80"/><f i="11" d="5,6,7,8"/><f i="12" d="65,66,67,68"/><f i="13" d="41,42,43,44"/><f i="14" d="97,98,99,100"/><f i="15" d="45,46,47,48"/><f i="16" d="117,118,119"/><f i="17" d="13,14,15,16"/><f i="18" d="81,82,83,84"/><f i="19" d="49,50,51,52"/><f i="20" d="101,102,103,104"/><f i="21" d="33,34,35,36"/><f i="22" d="21,22,23,24"/><f i="23" d="111,112,113"/><f i="24" d="25,26,27,28"/><f i="25" d="9,10,11,12"/><f i="26" d="108,109,110"/><f i="27" d="69,70,71,72"/><f i="28" d="114,115,116"/><f i="29" d="126,127,128"/><f i="30" d="37,38,39,40"/><f i="31" d="53,54,55,56"/><f i="32" d="120,121,122"/><f i="33" d="89,90,91,92"/><f i="34" d="1,2,3,4"/></map>
<map i="2"><f i="1" d="64,65,66"/><f i="2" d="103,104"/><f i="3" d="73,74,75"/><f i="4" d="99,100"/><f i="5" d="43,44,45"/><f i="6" d="10,11,12"/><f i="7" d="52,53,54"/><f i="8" d="115,116"/><f i="9" d="37,38,39"/><f i="10" d="55,56,57"/><f i="11" d="22,23,24"/><f i="12" d="125,126"/><f i="13" d="19,20,21"/><f i="14" d="28,29,30"/><f i="15" d="34,35,36"/><f i="16" d="31,32,33"/><f i="17" d="79,80,81"/><f i="18" d="97,98"/><f i="19" d="1,2,3"/><f i="20" d="119,120"/><f i="21" d="107,108"/><f i="22" d="82,83,84"/><f i="23" d="58,59,60"/><f i="24" d="88,89,90"/><f i="25" d="70,71,72"/><f i="26" d="123,124"/><f i="27" d="111,112"/><f i="28" d="76,77,78"/><f i="29" d="67,68,69"/><f i="30" d="13,14,15"/><f i="31" d="46,47,48"/><f i="32" d="49,50,51"/><f i="33" d="113,114"/><f i="34" d="85,86,87"/><f i="35" d="91,92,93"/><f i="36" d="94,95,96"/><f i="37" d="25,26,27"/><f i="38" d="105,106"/><f i="39" d="16,17,18"/><f i="40" d="109,110"/><f i="41" d="121,122"/><f i="42" d="7,8,9"/><f i="43" d="61,62,63"/><f i="44" d="101,102"/><f i="45" d="4,5,6"/><f i="46" d="117,118"/><f i="47" d="40,41,42"/><f i="48" d="127,128"/></map>
<map i="3"><f i="1" d="47,48"/><f i="2" d="57,58"/><f i="3" d="101,102"/><f i="4" d="69,70"/><f i="5" d="2"/><f i="6" d="7"/><f i="7" d="75,76"/><f i="8" d="22"/><f i="9" d="107,108"/><f i="10" d="12"/><f i="11" d="3"/><f i="12" d="31"/><f i="13" d="5"/><f i="14" d="26"/><f i="15" d="77,78"/><f i="16" d="123,124"/><f i="17" d="93,94"/><f i="18" d="10"/><f i="19" d="9"/><f i="20" d="36"/><f i="21" d="61,62"/><f i="22" d="49,50"/><f i="23" d="45,46"/><f i="24" d="4"/><f i="25" d="121,122"/><f i="26" d="1"/><f i="27" d="119,120"/><f i="28" d="87,88"/><f i="29" d="25"/><f i="30" d="27"/><f i="31" d="30"/><f i="32" d="95,96"/><f i="33" d="16"/><f i="34" d="91,92"/><f i="35" d="111,112"/><f i="36" d="29"/><f i="37" d="115,116"/><f i="38" d="23"/><f i="39" d="83,84"/><f i="40" d="125,126"/><f i="41" d="6"/><f i="42" d="21"/><f i="43" d="81,82"/><f i="44" d="113,114"/><f i="45" d="85,86"/><f i="46" d="117,118"/><f i="47" d="59,60"/><f i="48" d="35"/><f i="49" d="41,42"/><f i="50" d="43,44"/><f i="51" d="103,104"/><f i="52" d="32"/><f i="53" d="20"/><f i="54" d="28"/><f i="55" d="73,74"/><f i="56" d="63,64"/><f i="57" d="19"/><f i="58" d="34"/><f i="59" d="105,106"/><f i="60" d="89,90"/><f i="61" d="37,38"/><f i="62" d="11"/><f i="63" d="18"/><f i="64" d="39,40"/><f i="65" d="65,66"/><f i="66" d="53,54"/><f i="67" d="97,98"/><f i="68" d="24"/><f i="69" d="99,100"/><f i="70" d="67,68"/><f i="71" d="8"/><f i="72" d="109,110"/><f i="73" d="55,56"/><f i="74" d="33"/><f i="75" d="127,128"/><f i="76" d="14"/><f i="77" d="71,72"/><f i="78" d="13"/><f i="79" d="15"/><f i="80" d="17"/><f i="81" d="51,52"/><f i="82" d="79,80"/></map>
<map i="4"><f i="1" d="106"/><f i="2" d="76"/><f i="3" d="51"/><f i="4" d="9"/><f i="5" d="57"/><f i="6" d="77"/><f i="7" d="68"/><f i="8" d="78"/><f i="9" d="122"/><f i="10" d="43"/><f i="11" d="116"/><f i="12" d="103"/><f i="13" d="12"/><f i="14" d="56"/><f i="15" d="67"/><f i="16" d="27"/><f i="17" d="86"/><f i="18" d="79"/><f i="19" d="95"/><f i="20" d="26"/><f i="21" d="38"/><f i="22" d="11"/><f i="23" d="59"/><f i="24" d="20"/><f i="25" d="69"/><f i="26" d="65"/><f i="27" d="64"/><f i="28" d="30"/><f i="29" d="85"/><f i="30" d="82"/><f i="31" d="39"/><f i="32" d="23"/><f i="33" d="91"/><f i="34" d="36"/><f i="35" d="97"/><f i="36" d="62"/><f i="37" d="8"/><f i="38" d="25"/><f i="39" d="109"/><f i="40" d="94"/><f i="41" d="58"/><f i="42" d="108"/><f i="43" d="40"/><f i="44" d="61"/><f i="45" d="101"/><f i="46" d="89"/><f i="47" d="74"/><f i="48" d="105"/><f i="49" d="93"/><f i="50" d="5"/><f i="51" d="119"/><f i="52" d="42"/><f i="53" d="96"/><f i="54" d="114"/><f i="55" d="4"/><f i="56" d="2"/><f i="57" d="52"/><f i="58" d="48"/><f i="59" d="34"/><f i="60" d="124"/><f i="61" d="121"/><f i="62" d="113"/><f i="63" d="14"/><f i="64" d="45"/><f i="65" d="118"/><f i="66" d="123"/><f i="67" d="41"/><f i="68" d="100"/><f i="69" d="35"/><f i="70" d="98"/><f i="71" d="22"/><f i="72" d="44"/><f i="73" d="28"/><f i="74" d="17"/><f i="75" d="54"/><f i="76" d="92"/><f i="77" d="102"/><f i="78" d="50"/><f i="79" d="111"/><f i="80" d="75"/><f i="81" d="37"/><f i="82" d="24"/><f i="83" d="7"/><f i="84" d="46"/><f i="85" d="107"/><f i="86" d="15"/><f i="87" d="16"/><f i="88" d="125"/><f i="89" d="13"/><f i="90" d="32"/><f i="91" d="63"/><f i="92" d="19"/><f i="93" d="81"/><f i="94" d="90"/><f i="95" d="60"/><f i="96" d="110"/><f i="97" d="47"/><f i="98" d="33"/><f i="99" d="88"/><f i="100" d="117"/><f i="101" d="99"/><f i="102" d="3"/><f i="103" d="126"/><f i="104" d="83"/><f i="105" d="112"/><f i="106" d="73"/><f i="107" d="70"/><f i="108" d="55"/><f i="109" d="80"/><f i="110" d="87"/><f i="111" d="31"/><f i="112" d="104"/><f i="113" d="1"/><f i="114" d="72"/><f i="115" d="49"/><f i="116" d="115"/><f i="117" d="10"/><f i="118" d="120"/><f i="119" d="127"/><f i="120" d="29"/><f i="121" d="6"/><f i="122" d="66"/><f i="123" d="84"/><f i="124" d="18"/><f i="125" d="21"/><f i="126" d="128"/><f i="127" d="53"/><f i="128" d="71"/></map>
</maps>